{
  "phase": "phase-10-e2e-layer2-wasm-federation",
  "parentPhase": null,
  "childPhases": [],
  "childPointer": null,
  "assessment_complete": true,
  "plan_complete": true,
  "execute_complete": false,
  "reflect_complete": true,
  "changes_total": 6,
  "changes_completed": 6,
  "completed_changes": ["p10-c001-wasm-workspace-wiring", "p10-c002-compose-smoke", "p10-c003-layer2-e2e-specs", "p10-c004-kotlin-gradle-build", "p10-c005-criterion-regression-guard", "p10-c006-wasm-dagger-verify"],
  "active_change": null,
  "blocked_changes": [],
  "pending_changes": [],
  "execute_complete": true,
  "sourceTool": "kbd-execute",
  "createdBy": "kbd-next-phase",
  "updatedAt": "2026-06-22T17:30:00Z"
}
